{"_via_settings":{"ui":{"annotation_editor_height":25,"annotation_editor_fontsize":0.8,"leftsidebar_width":18,"image_grid":{"img_height":80,"rshape_fill":"none","rshape_fill_opacity":0.3,"rshape_stroke":"yellow","rshape_stroke_width":2,"show_region_shape":true,"show_image_policy":"all"},"image":{"region_label":"__via_region_id__","region_color":"__via_default_region_color__","region_label_font":"10px Sans","on_image_annotation_editor_placement":"NEAR_REGION"}},"core":{"buffer_size":18,"filepath":{},"default_filepath":""},"project":{"name":"via_project_6Feb2022_15h49m"}},"_via_img_metadata":{"0a242212407a8deee44953850aa8.jpeg25373":{"filename":"0a242212407a8deee44953850aa8.jpeg","size":25373,"regions":[{"shape_attributes":{"name":"polygon","all_points_x":[48,62,77,92,69],"all_points_y":[9,86,101,89,7]},"region_attributes":{"class":{"wrinkles":true}}},{"shape_attributes":{"name":"polygon","all_points_x":[104,261,247,299,319,332,339,346,332,320,267,223,146,96,74,122,156,168],"all_points_y":[152,150,100,109,86,89,146,219,263,279,230,206,201,181,132,77,75,99]},"region_attributes":{"class":{"wrinkles":true}}},{"shape_attributes":{"name":"polygon","all_points_x":[102,157,206,167,120],"all_points_y":[251,360,357,290,236]},"region_attributes":{"class":{"wrinkles":true}}},{"shape_attributes":{"name":"polygon","all_points_x":[7,1,69,63],"all_points_y":[93,127,126,99]},"region_attributes":{"class":{"wrinkles":true}}}],"file_attributes":{"caption":"","public_domain":"no","image_url":""}},"download.jpeg5549":{"filename":"download.jpeg","size":5549,"regions":[{"shape_attributes":{"name":"polygon","all_points_x":[117,103,194,195,118],"all_points_y":[33,49,47,34,32]},"region_attributes":{"class":{"wrinkles":true}}},{"shape_attributes":{"name":"polygon","all_points_x":[231,272,262,221],"all_points_y":[44,36,15,31]},"region_attributes":{"class":{"wrinkles":true}}},{"shape_attributes":{"name":"polygon","all_points_x":[22,22,57,67,31],"all_points_y":[20,33,48,39,12]},"region_attributes":{"class":{"wrinkles":true}}}],"file_attributes":{"caption":"","public_domain":"no","image_url":""}},"ds00890-sn7_wrinklesthu_jpg.jpeg20199":{"filename":"ds00890-sn7_wrinklesthu_jpg.jpeg","size":20199,"regions":[{"shape_attributes":{"name":"polygon","all_points_x":[144,90,115,172],"all_points_y":[262,323,334,276]},"region_attributes":{"class":{"wrinkles":true}}},{"shape_attributes":{"name":"polygon","all_points_x":[430,517,537,476,464],"all_points_y":[237,333,282,201,199]},"region_attributes":{"class":{"wrinkles":true}}}],"file_attributes":{"caption":"","public_domain":"no","image_url":""}},"image.jpeg887442":{"filename":"image.jpeg","size":887442,"regions":[{"shape_attributes":{"name":"polygon","all_points_x":[1228,1644,1784,1778,1693,1683,1625,1511,1290,1196,1196,1228],"all_points_y":[1290,1284,1297,1423,1527,1651,1729,1755,1752,1638,1446,1313]},"region_attributes":{"class":{"wrinkles":true}}},{"shape_attributes":{"name":"polygon","all_points_x":[1144,643,549,536,666,939,1092,1144],"all_points_y":[1654,1758,1680,1508,1534,1547,1544,1544]},"region_attributes":{"class":{"wrinkles":true}}},{"shape_attributes":{"name":"polygon","all_points_x":[1739,2255,2346,2450,2486,2441,2337,2333,1999],"all_points_y":[1544,1657,1596,1547,1449,1245,1290,1456,1459]},"region_attributes":{"class":{"wrinkles":true}}},{"shape_attributes":{"name":"polygon","all_points_x":[1713,2129,2210,1908,1761],"all_points_y":[1804,2249,2197,1787,1748]},"region_attributes":{"class":{"wrinkles":true}}},{"shape_attributes":{"name":"polygon","all_points_x":[1043,806,985,1137,1141],"all_points_y":[1817,2239,2259,1960,1810]},"region_attributes":{"class":{"wrinkles":true}}}],"file_attributes":{"caption":"","public_domain":"no","image_url":""}},"images_(1).jpeg6603":{"filename":"images_(1).jpeg","size":6603,"regions":[{"shape_attributes":{"name":"polygon","all_points_x":[38,181,239,237,154,75,40],"all_points_y":[82,27,39,80,78,106,124]},"region_attributes":{"class":{"wrinkles":true}}},{"shape_attributes":{"name":"polygon","all_points_x":[84,108,122,155,167,168,158],"all_points_y":[113,137,151,144,131,95,85]},"region_attributes":{"class":{"wrinkles":true}}},{"shape_attributes":{"name":"polygon","all_points_x":[175,231,242,247,247,226,191,190,205,264,263,249,187,166],"all_points_y":[98,107,125,133,152,166,165,176,185,184,129,88,84,82]},"region_attributes":{"class":{"wrinkles":true}}}],"file_attributes":{"caption":"","public_domain":"no","image_url":""}},"images_(2).jpeg5823":{"filename":"images_(2).jpeg","size":5823,"regions":[{"shape_attributes":{"name":"polygon","all_points_x":[33,238,228,72,30],"all_points_y":[61,76,25,20,24]},"region_attributes":{"class":{"wrinkles":true}}}],"file_attributes":{"caption":"","public_domain":"no","image_url":""}},"images_(3).jpeg5329":{"filename":"images_(3).jpeg","size":5329,"regions":[{"shape_attributes":{"name":"polygon","all_points_x":[93,67,67,76,99,103],"all_points_y":[20,68,95,95,54,31]},"region_attributes":{"class":{"wrinkles":true}}},{"shape_attributes":{"name":"polygon","all_points_x":[177,203,218,196,182],"all_points_y":[39,93,87,27,27]},"region_attributes":{"class":{"wrinkles":true}}}],"file_attributes":{"caption":"","public_domain":"no","image_url":""}},"images.jpeg5141":{"filename":"images.jpeg","size":5141,"regions":[{"shape_attributes":{"name":"polygon","all_points_x":[126,84,79,130,133],"all_points_y":[33,34,63,68,36]},"region_attributes":{"class":{"wrinkles":true}}},{"shape_attributes":{"name":"polygon","all_points_x":[113,91,93,114,122],"all_points_y":[111,138,160,137,123]},"region_attributes":{"class":{"wrinkles":true}}}],"file_attributes":{"caption":"","public_domain":"no","image_url":""}},"laughter-lines-mouth.jpeg54998":{"filename":"laughter-lines-mouth.jpeg","size":54998,"regions":[{"shape_attributes":{"name":"polygon","all_points_x":[371,235,253,290,295,318,382],"all_points_y":[74,292,562,567,369,259,144]},"region_attributes":{"class":{"wrinkles":true}}},{"shape_attributes":{"name":"polygon","all_points_x":[622,719,747,753,758,765,828,829,759,686,613],"all_points_y":[87,203,280,343,468,555,492,277,115,51,52]},"region_attributes":{"class":{"wrinkles":true}}},{"shape_attributes":{"name":"polygon","all_points_x":[307,144,100,101,155],"all_points_y":[10,63,60,25,5]},"region_attributes":{"class":{"wrinkles":true}}},{"shape_attributes":{"name":"polygon","all_points_x":[815,865,890,926,940,956,969,986,967,940,900,837],"all_points_y":[17,22,36,67,102,133,165,136,76,31,6,4]},"region_attributes":{"class":{"wrinkles":true}}},{"shape_attributes":{"name":"polygon","all_points_x":[388,512,581,636,657,665,664,598,492,422,405],"all_points_y":[527,497,502,512,522,542,553,553,538,541,551]},"region_attributes":{"class":{"wrinkles":true}}}],"file_attributes":{"caption":"","public_domain":"no","image_url":""}},"man-face-wrinkles-after-correction-260nw-1427596697.jpeg36936":{"filename":"man-face-wrinkles-after-correction-260nw-1427596697.jpeg","size":36936,"regions":[{"shape_attributes":{"name":"polygon","all_points_x":[114,71,63,63,90,116,132],"all_points_y":[81,144,185,205,193,135,105]},"region_attributes":{"class":{"wrinkles":true}}},{"shape_attributes":{"name":"polygon","all_points_x":[141,104,50,25,21,34,39,74,106,134],"all_points_y":[24,31,33,35,24,12,11,8,6,3]},"region_attributes":{"class":{"wrinkles":true}}}],"file_attributes":{"caption":"","public_domain":"no","image_url":""}},"UptownMedicalAesthetics-1175887624.jpeg107037":{"filename":"UptownMedicalAesthetics-1175887624.jpeg","size":107037,"regions":[{"shape_attributes":{"name":"polygon","all_points_x":[129,355,433,454,450,244,138,60,31,31,118],"all_points_y":[292,294,250,200,158,147,139,150,167,234,294]},"region_attributes":{"class":{"wrinkles":true}}},{"shape_attributes":{"name":"polygon","all_points_x":[236,206,275,324,326,315,310],"all_points_y":[311,368,410,410,362,318,302]},"region_attributes":{"class":{"wrinkles":true}}}],"file_attributes":{"caption":"","public_domain":"no","image_url":""}},"wrinkles_759.jpeg20279":{"filename":"wrinkles_759.jpeg","size":20279,"regions":[{"shape_attributes":{"name":"polygon","all_points_x":[357,358,370,429,456,469,427,414,400,382],"all_points_y":[107,104,83,83,96,109,120,141,151,147]},"region_attributes":{"class":{"wrinkles":true}}},{"shape_attributes":{"name":"polygon","all_points_x":[431,429,435,420,420,433,449,452,441],"all_points_y":[215,211,226,256,266,266,233,212,208]},"region_attributes":{"class":{"wrinkles":true}}}],"file_attributes":{"caption":"","public_domain":"no","image_url":""}},"0_cumberbach-1.jpg125063":{"filename":"0_cumberbach-1.jpg","size":125063,"regions":[{"shape_attributes":{"name":"polygon","all_points_x":[315,495,722,872,868,856,750,564,456,361],"all_points_y":[115,67,74,74,136,172,187,189,205,189]},"region_attributes":{"class":{"wrinkles":true}}},{"shape_attributes":{"name":"polygon","all_points_x":[282,237,210,194,194,217,236,309,390,456,480,481,390,299,268],"all_points_y":[358,349,344,404,478,540,576,548,504,488,466,444,423,438,401]},"region_attributes":{"class":{"wrinkles":true}}},{"shape_attributes":{"name":"polygon","all_points_x":[748,908,940,977,1004,1006,1013,1014,1014,934,880,841,801],"all_points_y":[419,440,481,500,500,481,430,375,308,356,371,380,380]},"region_attributes":{"class":{"wrinkles":true}}},{"shape_attributes":{"name":"polygon","all_points_x":[492,461,413,411,442,474,495],"all_points_y":[640,715,720,660,607,578,572]},"region_attributes":{"class":{"wrinkles":true}}},{"shape_attributes":{"name":"polygon","all_points_x":[676,738,770,810,823,813,765,720,691],"all_points_y":[569,629,665,665,646,600,566,540,540]},"region_attributes":{"class":{"wrinkles":true}}},{"shape_attributes":{"name":"polygon","all_points_x":[911,921,930,952,975,975,973,971,961,956],"all_points_y":[658,767,801,798,775,765,707,695,665,646]},"region_attributes":{"class":{"wrinkles":true}}}],"file_attributes":{"caption":"","public_domain":"no","image_url":""}},"face-wrinkles-1200.jpg73900":{"filename":"face-wrinkles-1200.jpg","size":73900,"regions":[{"shape_attributes":{"name":"polygon","all_points_x":[428,482,506,549,606,648,662,662,637,589,560,609,587,608,650,664,667,736,776,786,801,815,792,746,809,863,880,893,912,912,910,906,880,880,864,843,815,755,691,641,570,544,492,462,422,406,420],"all_points_y":[303,326,326,349,349,341,341,364,389,399,410,424,454,461,410,461,478,487,479,462,458,464,419,316,329,328,316,305,327,352,408,439,506,552,593,617,650,659,657,657,645,645,613,566,527,417,312]},"region_attributes":{"class":{"wrinkles":true}}},{"shape_attributes":{"name":"polygon","all_points_x":[698,697,697,736,736,736],"all_points_y":[270,308,339,335,290,270]},"region_attributes":{"class":{"wrinkles":true}}},{"shape_attributes":{"name":"polygon","all_points_x":[575,718,751,782,784,685,611,570],"all_points_y":[131,122,121,159,173,205,227,230]},"region_attributes":{"class":{"wrinkles":true}}}],"file_attributes":{"caption":"","public_domain":"no","image_url":""}},"file-20180313-30965-1mepa4q.jpg80387":{"filename":"file-20180313-30965-1mepa4q.jpg","size":80387,"regions":[{"shape_attributes":{"name":"polygon","all_points_x":[285,267,254,254,330,388,409,433,437,429,405],"all_points_y":[76,71,188,217,220,217,175,150,102,72,52]},"region_attributes":{"class":{"wrinkles":true}}},{"shape_attributes":{"name":"polygon","all_points_x":[525,501,501,585,641,684,709,730,731,717,708],"all_points_y":[76,188,232,232,241,250,273,262,224,173,89]},"region_attributes":{"class":{"wrinkles":true}}},{"shape_attributes":{"name":"polygon","all_points_x":[280,202,161,166,200,244,302,354,446,567,621,660,724,742,760,754,700,617,532,496,476,442,392,320],"all_points_y":[452,407,489,595,692,745,780,812,825,802,762,724,668,607,503,428,464,455,458,360,342,342,477,454]},"region_attributes":{"class":{"wrinkles":true}}},{"shape_attributes":{"name":"polygon","all_points_x":[433,410,443,483,489,490,490],"all_points_y":[170,241,269,269,241,206,144]},"region_attributes":{"class":{"wrinkles":true}}}],"file_attributes":{"caption":"","public_domain":"no","image_url":""}},"get-rid-of-wrinkles.jpg34414":{"filename":"get-rid-of-wrinkles.jpg","size":34414,"regions":[{"shape_attributes":{"name":"polygon","all_points_x":[235,187,161,162,177,204,223,236,237,245],"all_points_y":[74,71,53,22,19,12,10,9,9,9]},"region_attributes":{"class":{"wrinkles":true}}},{"shape_attributes":{"name":"polygon","all_points_x":[135,215,229,223,181,155,140],"all_points_y":[132,138,138,158,172,183,183]},"region_attributes":{"class":{"wrinkles":true}}},{"shape_attributes":{"name":"polygon","all_points_x":[163,146,145,145,155,171,186,200,223,229,239,227,205,196,196,186,186,189,192,216,217],"all_points_y":[215,232,250,278,301,306,311,311,311,311,295,293,291,284,281,265,249,243,236,213,189]},"region_attributes":{"class":{"wrinkles":true}}}],"file_attributes":{"caption":"","public_domain":"no","image_url":""}},"Male_Frowning_732x549-thumbnail.jpg132649":{"filename":"Male_Frowning_732x549-thumbnail.jpg","size":132649,"regions":[{"shape_attributes":{"name":"polygon","all_points_x":[271,350,382,392,402,402,378,349,326,299,283,279],"all_points_y":[181,174,175,186,207,220,221,221,220,220,220,220]},"region_attributes":{"class":{"wrinkles":true}}},{"shape_attributes":{"name":"polygon","all_points_x":[258,281,308,318,316,295,286,265],"all_points_y":[253,270,270,270,282,285,291,291]},"region_attributes":{"class":{"wrinkles":true}}},{"shape_attributes":{"name":"polygon","all_points_x":[358,388,399,408,408,408,409,410],"all_points_y":[277,295,299,294,289,277,273,269]},"region_attributes":{"class":{"wrinkles":true}}},{"shape_attributes":{"name":"polygon","all_points_x":[302,288,284,284,293,306,309],"all_points_y":[306,329,345,359,349,346,341]},"region_attributes":{"class":{"wrinkles":true}}},{"shape_attributes":{"name":"polygon","all_points_x":[357,373,375,387,397,392,376,360],"all_points_y":[313,333,357,356,346,326,300,297]},"region_attributes":{"class":{"wrinkles":true}}}],"file_attributes":{"caption":"","public_domain":"no","image_url":""}}},"_via_attributes":{"region":{"class":{"type":"checkbox","description":"","options":{"''":"","wrinkles":""},"default_options":{"wrinkles":true}}},"file":{"caption":{"type":"text","description":"","default_value":""},"public_domain":{"type":"radio","description":"","options":{"yes":"Yes","no":"No"},"default_options":{"no":true}},"image_url":{"type":"text","description":"","default_value":""}}},"_via_data_format_version":"2.0.10","_via_image_id_list":["0a242212407a8deee44953850aa8.jpeg25373","download.jpeg5549","ds00890-sn7_wrinklesthu_jpg.jpeg20199","image.jpeg887442","images_(1).jpeg6603","images_(2).jpeg5823","images_(3).jpeg5329","images.jpeg5141","laughter-lines-mouth.jpeg54998","man-face-wrinkles-after-correction-260nw-1427596697.jpeg36936","UptownMedicalAesthetics-1175887624.jpeg107037","wrinkles_759.jpeg20279","0_cumberbach-1.jpg125063","face-wrinkles-1200.jpg73900","file-20180313-30965-1mepa4q.jpg80387","get-rid-of-wrinkles.jpg34414","Male_Frowning_732x549-thumbnail.jpg132649"]}